gush_rag-0.1.42.dist-info/licenses/LICENSE
gushwork_rag/__init__.py
gushwork_rag/client.py
gushwork_rag/exceptions.py
gushwork_rag/http_client.py
gushwork_rag/models.py
gushwork_rag/clients/__init__.py
gushwork_rag/clients/assistant.py
gushwork_rag/clients/auth.py
gushwork_rag/clients/chat.py
gushwork_rag/clients/files.py
gushwork_rag/clients/namespaces.py
gushwork_rag/utils/__init__.py
gushwork_rag/utils/s3.py
gush_rag-0.1.42.dist-info/METADATA
gush_rag-0.1.42.dist-info/WHEEL
gush_rag-0.1.42.dist-info/top_level.txt
gush_rag-0.1.42.dist-info/RECORD
