Metadata-Version: 2.4
Name: gush-rag
Version: 0.1.42
Summary: Python SDK for the Gushwork Retrieval-Augmented Generation (RAG) API
Home-page: https://github.com/gushwork/gw-rag
Author: Gushwork
Author-email: support@gushwork.com
License: MIT
Keywords: rag,retrieval-augmented-generation,llm,ai,gushwork,sdk,api-client,chat,embeddings,vector-search
Classifier: Development Status :: 4 - Beta
Classifier: Intended Audience :: Developers
Classifier: License :: OSI Approved :: MIT License
Classifier: Programming Language :: Python :: 3
Classifier: Programming Language :: Python :: 3.10
Classifier: Programming Language :: Python :: 3.11
Classifier: Programming Language :: Python :: 3.12
Classifier: Topic :: Software Development :: Libraries :: Python Modules
Classifier: Topic :: Scientific/Engineering :: Artificial Intelligence
Requires-Python: >=3.8
License-File: LICENSE
Requires-Dist: requests>=2.25.0
Requires-Dist: boto3>=1.26.0
Requires-Dist: backoff>=2.2.0
Provides-Extra: dev
Requires-Dist: requests>=2.25.0; extra == "dev"
Requires-Dist: boto3>=1.26.0; extra == "dev"
Requires-Dist: backoff>=2.2.0; extra == "dev"
Dynamic: author-email
Dynamic: home-page
Dynamic: license-file
Dynamic: requires-python
